erbsland/conf_pygments/__init__.py
erbsland/conf_pygments/_version.py
erbsland/conf_pygments/lexer.py
erbsland_conf_pygments-1.0.0.dist-info/METADATA
erbsland_conf_pygments-1.0.0.dist-info/WHEEL
erbsland_conf_pygments-1.0.0.dist-info/entry_points.txt
erbsland_conf_pygments-1.0.0.dist-info/licenses/LICENSE
erbsland_conf_pygments-1.0.0.dist-info/RECORD
