Metadata-Version: 2.4
Name: erbsland-conf-pygments
Version: 1.0.0
Summary: The Pygments lexer for the Erbsland Configuration Language (ELCL)
Project-URL: Homepage, https://github.com/erbsland-dev/erbsland-pygments-conf
Project-URL: Issues, https://github.com/erbsland-dev/erbsland-pygments-conf/issues
Author-email: Tobias Erbsland / Erbsland DEV <info@erbsland.dev>
License:                                  Apache License
License-File: LICENSE
Requires-Python: >=3.12
Requires-Dist: erbsland-conf
Requires-Dist: pygments
